<?xml version="1.0" encoding="UTF-8"?>
<!DOCTYPE mapper PUBLIC "-//mybatis.org//DTD Mapper 3.0//EN" "http://mybatis.org/dtd/mybatis-3-mapper.dtd">
<mapper namespace="com.td.admin.mapper.SysJobErrorInfoMapper">
  <resultMap id="BaseResultMap" type="com.td.admin.entity.SysJobErrorInfo">
    <!--
      WARNING - @mbggenerated
      This element is automatically generated by MyBatis Generator, do not modify.
      This element was generated on Fri Aug 09 14:44:19 CST 2013.
    -->
    <id column="id" jdbcType="BIGINT" property="id" />
    <result column="jobKey" jdbcType="VARCHAR" property="jobkey" />
    <result column="createTime" jdbcType="TIMESTAMP" property="createtime" />
    <result column="MTime" jdbcType="TIMESTAMP" property="mtime" />
    <result column="CTime" jdbcType="TIMESTAMP" property="ctime" />
    <result column="jobInputId" jdbcType="INTEGER" property="jobinputid" />
  </resultMap>
  <resultMap extends="BaseResultMap" id="ResultMapWithBLOBs" type="com.td.admin.entity.SysJobErrorInfo">
    <!--
      WARNING - @mbggenerated
      This element is automatically generated by MyBatis Generator, do not modify.
      This element was generated on Fri Aug 09 14:44:19 CST 2013.
    -->
    <result column="errorInfo" jdbcType="LONGVARCHAR" property="errorinfo" />
  </resultMap>
  <sql id="Base_Column_List">
    <!--
      WARNING - @mbggenerated
      This element is automatically generated by MyBatis Generator, do not modify.
      This element was generated on Fri Aug 09 14:44:19 CST 2013.
    -->
    id, jobKey, createTime, MTime, CTime, jobInputId
  </sql>
  <sql id="Blob_Column_List">
    <!--
      WARNING - @mbggenerated
      This element is automatically generated by MyBatis Generator, do not modify.
      This element was generated on Fri Aug 09 14:44:19 CST 2013.
    -->
    errorInfo
  </sql>
  <select id="selectByPrimaryKey" parameterType="java.lang.Long" resultMap="ResultMapWithBLOBs">
    <!--
      WARNING - @mbggenerated
      This element is automatically generated by MyBatis Generator, do not modify.
      This element was generated on Fri Aug 09 14:44:19 CST 2013.
    -->
    select 
    <include refid="Base_Column_List" />
    ,
    <include refid="Blob_Column_List" />
    from SYS_JOB_ERRORINFO
    where id = #{id,jdbcType=BIGINT}
  </select>
  <delete id="deleteByPrimaryKey" parameterType="java.lang.Long">
    <!--
      WARNING - @mbggenerated
      This element is automatically generated by MyBatis Generator, do not modify.
      This element was generated on Fri Aug 09 14:44:19 CST 2013.
    -->
    delete from SYS_JOB_ERRORINFO
    where id = #{id,jdbcType=BIGINT}
  </delete>
  <insert id="insert" parameterType="com.td.admin.entity.SysJobErrorInfo">
    <!--
      WARNING - @mbggenerated
      This element is automatically generated by MyBatis Generator, do not modify.
      This element was generated on Fri Aug 09 14:44:19 CST 2013.
    -->
    insert into SYS_JOB_ERRORINFO (id, jobKey, createTime, 
      MTime, CTime, jobInputId, 
      errorInfo)
    values (#{id,jdbcType=BIGINT}, #{jobkey,jdbcType=VARCHAR}, #{createtime,jdbcType=TIMESTAMP}, 
      #{mtime,jdbcType=TIMESTAMP}, #{ctime,jdbcType=TIMESTAMP}, #{jobinputid,jdbcType=INTEGER}, 
      #{errorinfo,jdbcType=LONGVARCHAR})
  </insert>
  <insert id="insertSelective" parameterType="com.td.admin.entity.SysJobErrorInfo">
    <!--
      WARNING - @mbggenerated
      This element is automatically generated by MyBatis Generator, do not modify.
      This element was generated on Fri Aug 09 14:44:19 CST 2013.
    -->
    insert into SYS_JOB_ERRORINFO
    <trim prefix="(" suffix=")" suffixOverrides=",">
      <if test="id != null">
        id,
      </if>
      <if test="jobkey != null">
        jobKey,
      </if>
      <if test="createtime != null">
        createTime,
      </if>
      <if test="mtime != null">
        MTime,
      </if>
      <if test="ctime != null">
        CTime,
      </if>
      <if test="jobinputid != null">
        jobInputId,
      </if>
      <if test="errorinfo != null">
        errorInfo,
      </if>
    </trim>
    <trim prefix="values (" suffix=")" suffixOverrides=",">
      <if test="id != null">
        #{id,jdbcType=BIGINT},
      </if>
      <if test="jobkey != null">
        #{jobkey,jdbcType=VARCHAR},
      </if>
      <if test="createtime != null">
        #{createtime,jdbcType=TIMESTAMP},
      </if>
      <if test="mtime != null">
        #{mtime,jdbcType=TIMESTAMP},
      </if>
      <if test="ctime != null">
        #{ctime,jdbcType=TIMESTAMP},
      </if>
      <if test="jobinputid != null">
        #{jobinputid,jdbcType=INTEGER},
      </if>
      <if test="errorinfo != null">
        #{errorinfo,jdbcType=LONGVARCHAR},
      </if>
    </trim>
  </insert>
  <update id="updateByPrimaryKeySelective" parameterType="com.td.admin.entity.SysJobErrorInfo">
    <!--
      WARNING - @mbggenerated
      This element is automatically generated by MyBatis Generator, do not modify.
      This element was generated on Fri Aug 09 14:44:19 CST 2013.
    -->
    update SYS_JOB_ERRORINFO
    <set>
      <if test="jobkey != null">
        jobKey = #{jobkey,jdbcType=VARCHAR},
      </if>
      <if test="createtime != null">
        createTime = #{createtime,jdbcType=TIMESTAMP},
      </if>
      <if test="mtime != null">
        MTime = #{mtime,jdbcType=TIMESTAMP},
      </if>
      <if test="ctime != null">
        CTime = #{ctime,jdbcType=TIMESTAMP},
      </if>
      <if test="jobinputid != null">
        jobInputId = #{jobinputid,jdbcType=INTEGER},
      </if>
      <if test="errorinfo != null">
        errorInfo = #{errorinfo,jdbcType=LONGVARCHAR},
      </if>
    </set>
    where id = #{id,jdbcType=BIGINT}
  </update>
  <update id="updateByPrimaryKeyWithBLOBs" parameterType="com.td.admin.entity.SysJobErrorInfo">
    <!--
      WARNING - @mbggenerated
      This element is automatically generated by MyBatis Generator, do not modify.
      This element was generated on Fri Aug 09 14:44:19 CST 2013.
    -->
    update SYS_JOB_ERRORINFO
    set jobKey = #{jobkey,jdbcType=VARCHAR},
      createTime = #{createtime,jdbcType=TIMESTAMP},
      MTime = #{mtime,jdbcType=TIMESTAMP},
      CTime = #{ctime,jdbcType=TIMESTAMP},
      jobInputId = #{jobinputid,jdbcType=INTEGER},
      errorInfo = #{errorinfo,jdbcType=LONGVARCHAR}
    where id = #{id,jdbcType=BIGINT}
  </update>
  <update id="updateByPrimaryKey" parameterType="com.td.admin.entity.SysJobErrorInfo">
    <!--
      WARNING - @mbggenerated
      This element is automatically generated by MyBatis Generator, do not modify.
      This element was generated on Fri Aug 09 14:44:19 CST 2013.
    -->
    update SYS_JOB_ERRORINFO
    set jobKey = #{jobkey,jdbcType=VARCHAR},
      createTime = #{createtime,jdbcType=TIMESTAMP},
      MTime = #{mtime,jdbcType=TIMESTAMP},
      CTime = #{ctime,jdbcType=TIMESTAMP},
      jobInputId = #{jobinputid,jdbcType=INTEGER}
    where id = #{id,jdbcType=BIGINT}
  </update>
  
  <select id="getPagingCount" parameterType="com.td.admin.entity.SysJobErrorInfo" resultType="java.lang.Long">
  	select count(*) from  SYS_JOB_ERRORINFO 
  	where 1 = 1
  	  <if test="jobkey!=null and jobkey!=''">
       AND jobkey like '%${jobkey}%'
      </if>
      <if test="startcreatetime!=null and startcreatetime!=''">
      and createtime&gt;=#{startcreatetime,jdbcType=TIMESTAMP}
      </if>
       <if test="endcreatetime!=null and endcreatetime!=''">
       and createTime &lt;= date_format(#{endcreatetime,jdbcType=TIMESTAMP},'%Y-%c-%d 23:59:59') 
      </if>
        <if test="jobinputid!=null and jobinputid!=''">
      and jobInputId like '%${jobinputid}%'
      </if>
  </select>
  <select id="getPagingList" parameterType="java.util.Map" resultMap="BaseResultMap">
  	select <include refid="Base_Column_List" />,<include refid="Blob_Column_List" /> from SYS_JOB_ERRORINFO
  	where 1 = 1
  	   <if test="jobkey!=null and jobkey!=''">
       AND jobkey like '%${jobkey}%'
      </if>
      <if test="startcreatetime!=null and startcreatetime!=''">
      and createTime&gt;=#{startcreatetime,jdbcType=TIMESTAMP}
      </if>
       <if test="endcreatetime!=null and endcreatetime!=''">
       and createTime &lt;= date_format(#{endcreatetime,jdbcType=TIMESTAMP},'%Y-%c-%d 23:59:59') 
      </if>
         <if test="jobinputid!=null and jobinputid!=''">
      and jobInputId like '%${jobinputid}%'
      </if>
      order by createtime desc
      limit #{beginIndex,jdbcType=BIGINT},#{numPerPage,jdbcType=BIGINT}
  </select>
  
  <!-- 查询定时任务  -->
    <select id="queryJobError" parameterType="com.td.admin.entity.SysJobErrorInfo" resultMap="BaseResultMap">
		select <include refid="Base_Column_List" />,<include refid="Blob_Column_List" /> from SYS_JOB_ERRORINFO
  	  	where 1 = 1 
  	   <if test="jobkey!=null and jobkey!=''">
       AND jobkey like '%${jobkey}%'
      </if>
      <if test="startcreatetime!=null and startcreatetime!=''">
      and createTime&gt;=#{startcreatetime,jdbcType=TIMESTAMP}
      </if>
       <if test="endcreatetime!=null and endcreatetime!=''">
      and createTime&lt;=#{endcreatetime,jdbcType=TIMESTAMP}
      </if>
       <if test="jobinputid!=null and jobinputid!=''">
      and jobInputId like '%${jobinputid}%'
      </if>
      <if test="jobinputidCollection != null and jobinputidCollection !=''">
	   	and jobInputId in 
	  	<foreach collection="jobinputidList" item="item" index="index" open="(" separator="," close=")">  
	       #{item}  
	     </foreach>  
	  </if>
      order by createtime desc
      <if test="beginIndex != null and numPerPage != null" >
      	limit #{beginIndex,jdbcType=BIGINT}, #{numPerPage,jdbcType=BIGINT}
      </if>
      
  </select>
   <select id="selectCountqueryJobError" parameterType="com.td.admin.entity.SysJobErrorInfo" resultType="Integer">
		select count(*) from SYS_JOB_ERRORINFO
  	  	where 1 = 1 
  	   <if test="jobkey!=null and jobkey!=''">
       AND jobkey like '%${jobkey}%'
      </if>
      <if test="startcreatetime!=null and startcreatetime!=''">
      and createTime&gt;=#{startcreatetime,jdbcType=TIMESTAMP}
      </if>
       <if test="endcreatetime!=null and endcreatetime!=''">
      and createTime&lt;=#{endcreatetime,jdbcType=TIMESTAMP}
      </if>
       <if test="jobinputid!=null and jobinputid!=''">
      and jobInputId like '%${jobinputid}%'
      </if>
      <if test="jobinputidCollection != null and jobinputidCollection !=''">
	   	and jobInputId in 
	  	<foreach collection="jobinputidList" item="item" index="index" open="(" separator="," close=")">  
	       #{item}  
	     </foreach>  
	  </if>
  </select>
  
</mapper>